precise_scheduler/__init__.py
precise_scheduler/py.typed
schedule/__init__.py
schedule/py.typed
precise_scheduler-2.0.1b0.dist-info/AUTHORS.rst
precise_scheduler-2.0.1b0.dist-info/LICENSE.txt
precise_scheduler-2.0.1b0.dist-info/METADATA
precise_scheduler-2.0.1b0.dist-info/WHEEL
precise_scheduler-2.0.1b0.dist-info/top_level.txt
precise_scheduler-2.0.1b0.dist-info/RECORD
