Metadata-Version: 2.1
Name: precise-scheduler
Version: 2.0.1b0
Summary: Job scheduling for humans.
Home-page: https://github.com/bibinvargheset/precise_scheduler
Author: Bibin  Varghese
Author-email: bibinvargheset@gmail.com
License: MIT
Keywords: precise_scheduler,periodic,jobs,scheduling,clockwork,cron,precise_scheduler,job scheduling
Platform: UNKNOWN
Classifier: Intended Audience :: Developers
Classifier: License :: OSI Approved :: MIT License
Classifier: Development Status :: 5 - Production/Stable
Classifier: Operating System :: OS Independent
Classifier: Programming Language :: Python
Classifier: Programming Language :: Python :: 3.7
Classifier: Programming Language :: Python :: 3.8
Classifier: Programming Language :: Python :: 3.9
Classifier: Programming Language :: Python :: 3.10
Classifier: Programming Language :: Python :: 3.11
Classifier: Natural Language :: English
Requires-Python: >=3.6
License-File: LICENSE.txt
License-File: AUTHORS.rst
